{
  "debuffs": [
    {
      "key": "engulfing-storm",
      "type": "electro"
    },
    {
      "key": "slowing-water",
      "type": "hydro"
    },
    {
      "key": "smoldering-flames",
      "type": "pyro"
    },
    {
      "key": "condensed-ice",
      "type": "cryo"
    }
  ],
  "reactions": [
    {
      "key": "vaporize",
      "principal": [
        "pyro"
      ],
      "secondary": [
        "hydro"
      ]
    },
    {
      "key": "burning",
      "principal": [
        "pyro"
      ],
      "secondary": [
        "dendro"
      ]
    },
    {
      "key": "overloaded",
      "principal": [
        "pyro"
      ],
      "secondary": [
        "electro"
      ]
    },
    {
      "key": "melt",
      "principal": [
        "pyro"
      ],
      "secondary": [
        "cryo"
      ]
    },
    {
      "key": "vaporize-reverse",
      "principal": [
        "hydro"
      ],
      "secondary": [
        "pyro"
      ]
    },
    {
      "key": "electro-charged",
      "principal": [
        "hydro"
      ],
      "secondary": [
        "electro"
      ]
    },
    {
      "key": "frozen",
      "principal": [
        "hydro"
      ],
      "secondary": [
        "cryo"
      ]
    },
    {
      "key": "swirl",
      "principal": [
        "anemo"
      ],
      "secondary": [
        "pyro",
        "hydro",
        "electro",
        "cryo"
      ]
    },
    {
      "key": "superconduct",
      "principal": [
        "electro"
      ],
      "secondary": [
        "cryo"
      ]
    },
    {
      "key": "melt-reverse",
      "principal": [
        "cryo"
      ],
      "secondary": [
        "pyro"
      ]
    },
    {
      "key": "crystallize",
      "principal": [
        "geo"
      ],
      "secondary": [
        "pyro",
        "hydro",
        "electro",
        "cryo"
      ]
    }
  ],
  "resonance": [
    {
      "key": "enduring-rock",
      "principal": [
        "geo"
      ],
      "secondary": [
        "geo"
      ]
    },
    {
      "key": "fervent-flames",
      "principal": [
        "pyro"
      ],
      "secondary": [
        "pyro"
      ]
    },
    {
      "key": "soothing-waters",
      "principal": [
        "hydro"
      ],
      "secondary": [
        "hydro"
      ]
    },
    {
      "key": "impetuous-winds",
      "principal": [
        "anemo"
      ],
      "secondary": [
        "anemo"
      ]
    },
    {
      "key": "high-voltage",
      "principal": [
        "electro"
      ],
      "secondary": [
        "electro"
      ]
    },
    {
      "key": "shattering-ice",
      "principal": [
        "cryo"
      ],
      "secondary": [
        "cryo"
      ]
    },
    {
      "key": "protective-canopy",
      "principal": [],
      "secondary": []
    }
  ]
}